crispr_be_sensor/__init__.py
crispr_be_sensor/_demultiplex.py
crispr_be_sensor/_visualization.py
crispr_be_sensor-0.1.4.dist-info/METADATA
crispr_be_sensor-0.1.4.dist-info/WHEEL
crispr_be_sensor-0.1.4.dist-info/RECORD
